botblock/__init__.py
botblock/captcha.py
botblock/fonts/Amatic-Bold.ttf
botblock/fonts/LifeSavers-Bold.ttf
botblock/fonts/SIL Open Font License Amatic-Bold.txt
botblock/fonts/SIL Open Font License LifeSavers-Bold.txt
botblock/fonts/TungusFont_Tinet.ttf
botblock/fonts/TungusFonts.txt
botblock-2.1.0.dist-info/LICENSE
botblock-2.1.0.dist-info/METADATA
botblock-2.1.0.dist-info/WHEEL
botblock-2.1.0.dist-info/top_level.txt
botblock-2.1.0.dist-info/RECORD
