Metadata-Version: 2.1
Name: botblock
Version: 2.1.0
Summary: A modern, self-hosted, privacy-respecting, CAPTCHA solution
Author-email: Priveasy <Admin@Priveasy.org>
License: MIT License
Project-URL: Repository, https://source.priveasy.org/Priveasy/bot-block
Keywords: BotBlock,bot-block,Bot,Block,CAPTCHA,Spam,Protect,Form,Website,Self-Hosted,Self,Hosted,Privacy,Priveasy,P5vc
Classifier: Programming Language :: Python :: 3
Classifier: License :: OSI Approved :: MIT License
Classifier: Operating System :: OS Independent
Requires-Python: >=3.9
License-File: LICENSE
Requires-Dist: cryptography (>=39.0)
Requires-Dist: importlib-resources (>=5.12)
Requires-Dist: Pillow (>=9.4)
